odoo/addons/account_tax_repartition_line_tax_group_account/README.rst
odoo/addons/account_tax_repartition_line_tax_group_account/__init__.py
odoo/addons/account_tax_repartition_line_tax_group_account/__manifest__.py
odoo/addons/account_tax_repartition_line_tax_group_account/i18n/account_tax_repartition_line_tax_group_account.pot
odoo/addons/account_tax_repartition_line_tax_group_account/models/__init__.py
odoo/addons/account_tax_repartition_line_tax_group_account/models/account_tax_group.py
odoo/addons/account_tax_repartition_line_tax_group_account/models/account_tax_repartition_line.py
odoo/addons/account_tax_repartition_line_tax_group_account/readme/CONFIGURE.rst
odoo/addons/account_tax_repartition_line_tax_group_account/readme/CONTRIBUTORS.rst
odoo/addons/account_tax_repartition_line_tax_group_account/readme/DESCRIPTION.rst
odoo/addons/account_tax_repartition_line_tax_group_account/readme/USAGE.rst
odoo/addons/account_tax_repartition_line_tax_group_account/static/description/icon.png
odoo/addons/account_tax_repartition_line_tax_group_account/static/description/index.html
odoo/addons/account_tax_repartition_line_tax_group_account/tests/__init__.py
odoo/addons/account_tax_repartition_line_tax_group_account/tests/test_account_tax_repartition_line_tax_group_account.py
odoo/addons/account_tax_repartition_line_tax_group_account/views/account_tax_group_views.xml
odoo13_addon_account_tax_repartition_line_tax_group_account-13.0.1.0.1.dev3.dist-info/METADATA
odoo13_addon_account_tax_repartition_line_tax_group_account-13.0.1.0.1.dev3.dist-info/WHEEL
odoo13_addon_account_tax_repartition_line_tax_group_account-13.0.1.0.1.dev3.dist-info/top_level.txt
odoo13_addon_account_tax_repartition_line_tax_group_account-13.0.1.0.1.dev3.dist-info/RECORD
