Metadata-Version: 2.1
Name: odoo13-addon-account-tax-repartition-line-tax-group-account
Version: 13.0.1.0.1.dev3
Summary: Set a default account from tax group to tax repartition lines
Home-page: https://github.com/OCA/account-financial-tools
Author: ForgeFlow,Odoo Community Association (OCA)
Author-email: support@odoo-community.org
License: LGPL-3
Platform: UNKNOWN
Classifier: Programming Language :: Python
Classifier: Framework :: Odoo
Classifier: Framework :: Odoo :: 13.0
Classifier: License :: OSI Approved :: GNU Lesser General Public License v3 (LGPLv3)
Requires-Python: >=3.5
Requires-Dist: odoo <13.1dev,>=13.0a
